quantum_docker/__init__.py
quantum_docker/cli/__init__.py
quantum_docker/cli/__main__.py
quantum_docker/cli/cli.py
quantum_docker/cli/state_manager.py
quantum_docker/containers/__init__.py
quantum_docker/containers/quantum_container.py
quantum_docker/core/__init__.py
quantum_docker/core/engine.py
quantum_docker/core/quantum_resource_manager.py
quantum_docker/monitoring/__init__.py
quantum_docker/monitoring/quantum_monitor.py
quantum_docker/networking/__init__.py
quantum_docker/networking/quantum_network.py
quantum_docker/quantum/__init__.py
quantum_docker/quantum/circuit_manager.py
quantum_docker/quantum/quantum_algorithms.py
quantum_docker/quantum/quantum_error_correction.py
quantum_docker/quantum/quantum_process_simulator.py
quantum_docker_engine-1.0.4.dist-info/licenses/LICENSE
quantum_docker_engine-1.0.4.dist-info/METADATA
quantum_docker_engine-1.0.4.dist-info/WHEEL
quantum_docker_engine-1.0.4.dist-info/entry_points.txt
quantum_docker_engine-1.0.4.dist-info/top_level.txt
quantum_docker_engine-1.0.4.dist-info/RECORD
