Metadata-Version: 2.4
Name: quantum-docker-engine
Version: 1.0.4
Summary: Revolutionary container orchestration engine powered by quantum computing
Home-page: https://github.com/quantum-docker/engine
Author: Quantum Docker Team
Author-email: contact@quantumdocker.io
Keywords: quantum computing,container orchestration,docker,kubernetes,quantum algorithms
Classifier: Development Status :: 4 - Beta
Classifier: Intended Audience :: Developers
Classifier: Topic :: Software Development :: Libraries :: Python Modules
Classifier: Topic :: System :: Distributed Computing
Classifier: License :: OSI Approved :: MIT License
Classifier: Programming Language :: Python :: 3
Classifier: Programming Language :: Python :: 3.8
Classifier: Programming Language :: Python :: 3.9
Classifier: Programming Language :: Python :: 3.10
Classifier: Programming Language :: Python :: 3.11
Classifier: Programming Language :: Python :: 3.12
Requires-Python: >=3.8
License-File: LICENSE
Requires-Dist: cirq<1.7.0,>=1.3.0
Requires-Dist: numpy<2.0.0,>=1.21.0
Requires-Dist: docker>=6.1.3
Requires-Dist: click>=8.1.7
Requires-Dist: pyyaml>=6.0.1
Requires-Dist: rich>=13.7.0
Requires-Dist: typing-extensions>=4.8.0
Requires-Dist: matplotlib>=3.7.2
Requires-Dist: scipy<2.0.0,>=1.11.0
Requires-Dist: networkx<4.0.0,>=3.1
Requires-Dist: psutil>=5.9.5
Requires-Dist: protobuf<6.0,>=5.26
Requires-Dist: attrs>=23.1.0
Provides-Extra: dev
Requires-Dist: pytest>=7.0.0; extra == "dev"
Requires-Dist: black>=22.0.0; extra == "dev"
Requires-Dist: flake8>=4.0.0; extra == "dev"
Requires-Dist: mypy>=1.0.0; extra == "dev"
Requires-Dist: pytest-asyncio>=0.21.0; extra == "dev"
Provides-Extra: docs
Requires-Dist: sphinx>=5.0.0; extra == "docs"
Requires-Dist: sphinx-rtd-theme>=1.2.0; extra == "docs"
Provides-Extra: qiskit
Requires-Dist: qiskit<3.0.0,>=0.45.0; extra == "qiskit"
Dynamic: author
Dynamic: author-email
Dynamic: classifier
Dynamic: description
Dynamic: description-content-type
Dynamic: home-page
Dynamic: keywords
Dynamic: license-file
Dynamic: provides-extra
Dynamic: requires-dist
Dynamic: requires-python
Dynamic: summary
